colink/__init__.py
colink/application.py
colink/colink.py
colink/instant_server.py
colink/lock_key.py
colink/p2p_inbox.py
colink/participant_id.py
colink/policy_module.py
colink/protocol.py
colink/read_wait.py
colink/registry.py
colink/remote_storage.py
colink/switch_to_generated_user.py
colink/tls_utils.py
colink/variable_transfer.py
colink/wait_task_end.py
colink/wait_user_init_func.py
colink/proto/__init__.py
colink/proto/colink_pb2.py
colink/proto/colink_pb2_grpc.py
colink/proto/colink_policy_module_pb2.py
colink/proto/colink_registry_pb2.py
colink/proto/colink_remote_storage_pb2.py
colink/proto/proto_gen.py
colink/proto/v3/__init__.py
colink/proto/v3/colink_pb2.py
colink/proto/v3/colink_pb2_grpc.py
colink/proto/v3/colink_policy_module_pb2.py
colink/proto/v3/colink_registry_pb2.py
colink/proto/v3/colink_remote_storage_pb2.py
colink/proto/v4/__init__.py
colink/proto/v4/colink_pb2.py
colink/proto/v4/colink_pb2_grpc.py
colink/proto/v4/colink_policy_module_pb2.py
colink/proto/v4/colink_registry_pb2.py
colink/proto/v4/colink_remote_storage_pb2.py
colink-0.3.7.dist-info/LICENSE
colink-0.3.7.dist-info/METADATA
colink-0.3.7.dist-info/WHEEL
colink-0.3.7.dist-info/top_level.txt
colink-0.3.7.dist-info/RECORD
