Metadata-Version: 2.1
Name: colink
Version: 0.3.7
Summary: colink python module
Author: Wenjie Qu
Author-email: 
License-File: LICENSE
Requires-Dist: grpcio >=1.27.2
Requires-Dist: protobuf <5.0dev,>=3.19.0
Requires-Dist: coincurve >=18.0.0
Requires-Dist: cryptography >=39.0.1
Requires-Dist: pika >=1.2.0
Requires-Dist: pyjwt >=2.6.0
Requires-Dist: requests >=2.28.1
Requires-Dist: requests-toolbelt >=0.10.1
Requires-Dist: redis >=4.5.4
